confee/__init__.py
confee/async_loader.py
confee/colors.py
confee/config.py
confee/error_formatter.py
confee/help_formatter.py
confee/loaders.py
confee/overrides.py
confee/parser.py
confee/plugins.py
confee/py.typed
confee/schema.py
confee-0.3.3.dist-info/licenses/LICENSE
confee-0.3.3.dist-info/METADATA
confee-0.3.3.dist-info/WHEEL
confee-0.3.3.dist-info/top_level.txt
confee-0.3.3.dist-info/RECORD
