Metadata-Version: 2.4
Name: confee
Version: 0.3.3
Summary: Configuration Enhanced & Easy ☕️ - A Hydra-like configuration parser helper package
Author-email: JunSeok Kim <infend@gmail.com>
License: MIT
Project-URL: Homepage, https://github.com/bestend/confee
Project-URL: Documentation, https://github.com/bestend/confee#readme
Project-URL: Repository, https://github.com/bestend/confee.git
Project-URL: Issues, https://github.com/bestend/confee/issues
Keywords: configuration,config,parser,hydra,pydantic,yaml
Classifier: Development Status :: 3 - Alpha
Classifier: Intended Audience :: Developers
Classifier: License :: OSI Approved :: MIT License
Classifier: Programming Language :: Python :: 3
Classifier: Programming Language :: Python :: 3.12
Classifier: Programming Language :: Python :: 3.13
Classifier: Programming Language :: Python :: 3.14
Classifier: Topic :: Software Development :: Libraries :: Python Modules
Requires-Python: >=3.12
License-File: LICENSE
Requires-Dist: devtools>=0.12.2
Requires-Dist: pydantic>=2.0.0
Requires-Dist: PyYAML>=6.0
Requires-Dist: typing-extensions>=4.0.0
Provides-Extra: cli
Requires-Dist: typer>=0.9.0; extra == "cli"
Provides-Extra: remote
Requires-Dist: aiohttp>=3.8.0; extra == "remote"
Provides-Extra: toml
Provides-Extra: all
Requires-Dist: typer>=0.9.0; extra == "all"
Requires-Dist: aiohttp>=3.8.0; extra == "all"
Provides-Extra: dev
Requires-Dist: pytest>=7.0.0; extra == "dev"
Requires-Dist: pytest-cov>=4.0.0; extra == "dev"
Requires-Dist: pytest-mock>=3.10.0; extra == "dev"
Requires-Dist: pytest-asyncio>=0.21.0; extra == "dev"
Requires-Dist: black>=23.0.0; extra == "dev"
Requires-Dist: ruff>=0.1.0; extra == "dev"
Requires-Dist: mypy>=1.0.0; extra == "dev"
Requires-Dist: types-PyYAML>=6.0.0; extra == "dev"
Dynamic: license-file
